{
    "Ar36": {
        "error": 0.0002529203296079674,
        "error_type": "SEM",
        "filter_outliers_dict": {
            "filter_outliers": true,
            "iterations": 1,
            "std_devs": 2
        },
        "fit": "Linear",
        "value": 0.010100800741864983
    },
    "Ar37": {
        "error": 0.009684885745724299,
        "error_type": "SEM",
        "filter_outliers_dict": {
            "filter_outliers": true,
            "iterations": 1,
            "std_devs": 2
        },
        "fit": "Linear",
        "value": 0.8762734774666419
    },
    "Ar38": {
        "error": 0.011644441347347101,
        "error_type": "SEM",
        "filter_outliers_dict": {
            "filter_outliers": true,
            "iterations": 1,
            "std_devs": 2
        },
        "fit": "Linear",
        "value": 0.0542922247215345
    },
    "Ar39": {
        "error": 0.008940380494741074,
        "error_type": "SEM",
        "filter_outliers_dict": {
            "filter_outliers": true,
            "iterations": 1,
            "std_devs": 2
        },
        "fit": "Linear",
        "value": 3.645163054310443
    },
    "Ar40": {
        "error": 0.06297252440291105,
        "error_type": "SEM",
        "filter_outliers_dict": {
            "filter_outliers": true,
            "iterations": 1,
            "std_devs": 2
        },
        "fit": "Linear",
        "value": 791.044971072693
    }
}